{"route": "45", "destination": "Broad-Oregon", "day": "Saturday", "stops": [{"times": ["5:19am", "5:38am", "5:53am", "6:08am", "6:23am", "6:38am", "6:53am", "7:08am", "7:24am", "7:39am", "7:54am", "8:09am", "8:25am", "8:40am", "8:55am", "9:10am", "9:25am", "9:40am", "9:54am", "10:09am", "10:24am", "10:39am", "10:53am", "11:07am", "11:21am", "11:35am", "11:49am", "12:03pm", "12:17pm", "12:31pm", "12:45pm", "12:58pm", "1:11pm", "1:24pm", "1:37pm", "1:50pm", "2:03pm", "2:16pm", "2:29pm", "2:42pm", "2:55pm", "3:08pm", "3:21pm", "3:34pm", "3:47pm", "4:00pm", "4:13pm", "4:27pm", "4:41pm", "4:55pm", "5:09pm", "5:24pm", "5:39pm", "5:54pm", "6:09pm", "6:24pm", "6:39pm", "6:54pm", "7:10pm", "7:26pm", "7:44pm", "8:02pm", "8:21pm", "8:40pm", "9:00pm", "9:21pm", "9:42pm", "10:03pm", "10:24pm", "10:47pm", "11:11pm", "11:34pm", "11:58pm", "12:26am", "12:56am", "1:26am", "1:56am"], "name": "12th & Noble Sts.", "id": "32308"}, {"times": ["5:22am", "5:41am", "5:56am", "6:12am", "6:27am", "6:42am", "6:57am", "7:13am", "7:29am", "7:44am", "7:59am", "8:14am", "8:30am", "8:45am", "9:00am", "9:15am", "9:30am", "9:45am", "9:59am", "10:14am", "10:29am", "10:44am", "10:58am", "11:12am", "11:26am", "11:40am", "11:54am", "12:08pm", "12:22pm", "12:36pm", "12:50pm", "1:03pm", "1:16pm", "1:29pm", "1:42pm", "1:55pm", "2:08pm", "2:21pm", "2:34pm", "2:47pm", "3:00pm", "3:13pm", "3:26pm", "3:39pm", "3:52pm", "4:05pm", "4:18pm", "4:32pm", "4:46pm", "5:00pm", "5:14pm", "5:29pm", "5:44pm", "5:59pm", "6:14pm", "6:29pm", "6:44pm", "6:59pm", "7:14pm", "7:30pm", "7:48pm", "8:06pm", "8:25pm", "8:44pm", "9:04pm", "9:25pm", "9:46pm", "10:07pm", "10:28pm", "10:51pm", "11:14pm", "11:37pm", "12:01am", "12:29am", "12:59am", "1:29am", "1:59am"], "name": "12th & Market Sts.", "id": "756"}, {"times": ["5:28am", "5:47am", "6:03am", "6:19am", "6:34am", "6:49am", "7:04am", "7:20am", "7:36am", "7:51am", "8:06am", "8:21am", "8:37am", "8:52am", "9:07am", "9:22am", "9:37am", "9:52am", "10:08am", "10:23am", "10:38am", "10:53am", "11:07am", "11:21am", "11:35am", "11:49am", "12:04pm", "12:18pm", "12:32pm", "12:46pm", "1:00pm", "1:13pm", "1:26pm", "1:39pm", "1:52pm", "2:05pm", "2:18pm", "2:31pm", "2:44pm", "2:57pm", "3:10pm", "3:23pm", "3:36pm", "3:49pm", "4:02pm", "4:15pm", "4:28pm", "4:42pm", "4:56pm", "5:09pm", "5:23pm", "5:38pm", "5:53pm", "6:08pm", "6:23pm", "6:38pm", "6:53pm", "7:08pm", "7:23pm", "7:39pm", "7:57pm", "8:15pm", "8:34pm", "8:53pm", "9:12pm", "9:33pm", "9:54pm", "10:15pm", "10:36pm", "10:59pm", "11:21pm", "11:44pm", "12:07am", "12:35am", "1:05am", "1:35am", "2:05am"], "name": "12th St. & Washington Ave.", "id": "1181"}, {"times": ["5:42am", "6:01am", "6:18am", "6:34am", "6:49am", "7:04am", "7:19am", "7:35am", "7:51am", "8:06am", "8:21am", "8:36am", "8:52am", "9:07am", "9:23am", "9:38am", "9:53am", "10:08am", "10:24am", "10:39am", "10:54am", "11:09am", "11:23am", "11:37am", "11:51am", "12:05pm", "12:20pm", "12:34pm", "12:48pm", "1:02pm", "1:16pm", "1:29pm", "1:42pm", "1:55pm", "2:08pm", "2:21pm", "2:34pm", "2:47pm", "3:00pm", "3:13pm", "3:26pm", "3:39pm", "3:52pm", "4:05pm", "4:18pm", "4:31pm", "4:44pm", "4:58pm", "5:12pm", "5:25pm", "5:39pm", "5:54pm", "6:09pm", "6:24pm", "6:39pm", "6:54pm", "7:09pm", "7:24pm", "7:39pm", "7:55pm", "8:13pm", "8:31pm", "8:50pm", "9:09pm", "9:27pm", "9:48pm", "10:09pm", "10:30pm", "10:51pm", "11:14pm", "11:35pm", "11:58pm", "12:20am", "12:48am", "1:18am", "1:48am", "2:18am"], "name": "Broad St. & Oregon Ave.", "id": "20959"}]}