[{"lng":-75.536039,"lat":40.133516,"stopid":1707,"stopname":"Phoenixville Plaza"},{"lng":-75.547575,"lat":40.179625,"stopid":1708,"stopname":"New St &amp; Main St"},{"lng":-75.525709,"lat":40.199566,"stopid":1709,"stopname":"Limerick Square Shopping Center"},{"lng":-75.547717,"lat":40.179768,"stopid":1711,"stopname":"Main St &amp; New St"},{"lng":-75.393107,"lat":40.089829,"stopid":1827,"stopname":"Plaza at King of Prussia"},{"lng":-75.415918,"lat":40.092413,"stopid":10909,"stopname":"North Gulph Rd &amp; Freedom Business C"},{"lng":-75.413091,"lat":40.089932,"stopid":10910,"stopname":"North Gulph Rd &amp; Guthrie Rd"},{"lng":-75.412913,"lat":40.089575,"stopid":14984,"stopname":"North Gulph Rd &amp; Guthrie Rd - FS"},{"lng":-75.417515,"lat":40.095671,"stopid":19687,"stopname":"North Gulph Rd &amp; 1st Av"},{"lng":-75.515865,"lat":40.132728,"stopid":19688,"stopname":"Main St &amp; Church St - FS"},{"lng":-75.417219,"lat":40.095859,"stopid":19689,"stopname":"North Gulph Rd &amp; 1st Av - MBFS"},{"lng":-75.515723,"lat":40.132809,"stopid":19690,"stopname":"Main St &amp; Church St"},{"lng":-75.481458,"lat":40.112192,"stopid":19691,"stopname":"Valley Forge Rd &amp; Ferry Ln"},{"lng":-75.481589,"lat":40.112049,"stopid":19692,"stopname":"Valley Forge Rd &amp; Country Club Rd -"},{"lng":-75.500235,"lat":40.214561,"stopid":20420,"stopname":"Township Line Rd &amp; Ridge Pk - FS"},{"lng":-75.518352,"lat":40.133771,"stopid":27887,"stopname":"Bridge St &amp; Gay St"},{"lng":-75.420461,"lat":40.100929,"stopid":28851,"stopname":"North Gulph Rd &amp; Valley Forge Rd - "},{"lng":-75.436105,"lat":40.104455,"stopid":28853,"stopname":"Valley Forge Park Dr &amp; Washington M"},{"lng":-75.461641,"lat":40.100024,"stopid":28854,"stopname":"Valley Forge Rd &amp; Valley Creek Rd"},{"lng":-75.477407,"lat":40.106374,"stopid":28858,"stopname":"Valley Forge Rd &amp; Eastgate Dr"},{"lng":-75.484585,"lat":40.115118,"stopid":28862,"stopname":"Valley Forge Rd &amp; Lafayette Rd"},{"lng":-75.488162,"lat":40.117981,"stopid":28863,"stopname":"Valley Forge Rd &amp; McAvoy Ln"},{"lng":-75.497894,"lat":40.12044,"stopid":28864,"stopname":"Valley Forge Rd &amp; Morehall Dr"},{"lng":-75.502936,"lat":40.120089,"stopid":28866,"stopname":"Valley Forge Rd &amp; Whitehorse Rd"},{"lng":-75.513382,"lat":40.12559,"stopid":28872,"stopname":"Main St &amp; 5th Av"},{"lng":-75.514024,"lat":40.127526,"stopid":28874,"stopname":"Main St &amp; 3rd Av"},{"lng":-75.514641,"lat":40.129445,"stopid":28876,"stopname":"Main St &amp; 1st Av"},{"lng":-75.51495,"lat":40.130435,"stopid":28877,"stopname":"Main St &amp; Washington Av"},{"lng":-75.51857,"lat":40.137814,"stopid":28879,"stopname":"Franklin St &amp; High St"},{"lng":-75.52166,"lat":40.137633,"stopid":28880,"stopname":"High St &amp; Fairview St"},{"lng":-75.523945,"lat":40.137337,"stopid":28881,"stopname":"High St &amp; Taylor St"},{"lng":-75.532104,"lat":40.13858,"stopid":28882,"stopname":"Mowere Rd &amp; Northridge Dr - FS"},{"lng":-75.53878,"lat":40.137539,"stopid":28884,"stopname":"Township Line Rd &amp; Szabo Farm Ln"},{"lng":-75.535197,"lat":40.13233,"stopid":28885,"stopname":"Schuylkill Rd &amp; Kimberton Rd - FS"},{"lng":-75.543456,"lat":40.136982,"stopid":28886,"stopname":"Schuylkill Rd &amp; Otis Ln - MBNS"},{"lng":-75.546646,"lat":40.140237,"stopid":28888,"stopname":"Schuylkill Rd &amp; Mowere Rd - FS"},{"lng":-75.54844,"lat":40.144323,"stopid":28889,"stopname":"Schuylkill Rd &amp; Ridge Rd - FS"},{"lng":-75.551535,"lat":40.154005,"stopid":28891,"stopname":"Schuylkill Rd &amp; Hares Hill Rd"},{"lng":-75.553154,"lat":40.158636,"stopid":28892,"stopname":"Schuylkill Rd &amp; Spring Hollow Rd"},{"lng":-75.558487,"lat":40.173911,"stopid":28895,"stopname":"Schuylkill Rd &amp; Park Rd"},{"lng":-75.557234,"lat":40.175626,"stopid":28896,"stopname":"New St &amp; Vincent Heights Cr - FS"},{"lng":-75.551292,"lat":40.178069,"stopid":28898,"stopname":"New St &amp; Penn St"},{"lng":-75.549126,"lat":40.178972,"stopid":28899,"stopname":"New St &amp; Church St"},{"lng":-75.548264,"lat":40.180955,"stopid":28900,"stopname":"Main St &amp; Yost St - MBFS"},{"lng":-75.543434,"lat":40.182932,"stopid":28903,"stopname":"Main St &amp; 1st Av - MBFS"},{"lng":-75.5409,"lat":40.183657,"stopid":28905,"stopname":"Main St &amp; 3rd Av"},{"lng":-75.539125,"lat":40.185105,"stopid":28906,"stopname":"Main St &amp; 4th Av"},{"lng":-75.537563,"lat":40.1864,"stopid":28907,"stopname":"Main St &amp; 5th Av"},{"lng":-75.534522,"lat":40.188884,"stopid":28909,"stopname":"Main St &amp; 7th Av"},{"lng":-75.532143,"lat":40.19085,"stopid":28910,"stopname":"Main St &amp; Lewis Rd"},{"lng":-75.532037,"lat":40.19118,"stopid":28919,"stopname":"Main St &amp; Lewis Rd"},{"lng":-75.53754,"lat":40.186641,"stopid":28922,"stopname":"Main St &amp; 5th Av"},{"lng":-75.539101,"lat":40.185337,"stopid":28923,"stopname":"Main St &amp; 4th Av"},{"lng":-75.540379,"lat":40.184291,"stopid":28924,"stopname":"Main St &amp; 3rd Av"},{"lng":-75.542285,"lat":40.183361,"stopid":28925,"stopname":"Main St &amp; 2nd Av"},{"lng":-75.548346,"lat":40.180606,"stopid":28928,"stopname":"Main St &amp; Yost St"},{"lng":-75.548972,"lat":40.179196,"stopid":28929,"stopname":"New St &amp; Church St"},{"lng":-75.551174,"lat":40.178283,"stopid":28930,"stopname":"New St &amp; Penn St"},{"lng":-75.557187,"lat":40.175778,"stopid":28932,"stopname":"New St &amp; Schuykill Rd - MBNS"},{"lng":-75.558867,"lat":40.174277,"stopid":28933,"stopname":"Schuylkill Rd Rd &amp; Cypress Av"},{"lng":-75.553367,"lat":40.158591,"stopid":28936,"stopname":"Schuylkill Rd &amp; Bonnie Brae Rd"},{"lng":-75.551177,"lat":40.152264,"stopid":28937,"stopname":"Schuylkill Rd &amp; Hares Hill Rd - MBF"},{"lng":-75.548522,"lat":40.143573,"stopid":28939,"stopname":"Schuylkill Rd &amp; Ridge Rd"},{"lng":-75.542922,"lat":40.136143,"stopid":28942,"stopname":"Schuylkill Rd &amp; Shoppes at Valley F"},{"lng":-75.538626,"lat":40.137406,"stopid":28943,"stopname":"Township Line Rd &amp; Westridge Dr"},{"lng":-75.533418,"lat":40.138454,"stopid":28945,"stopname":"Mowere Rd &amp; Westridge Dr"},{"lng":-75.524205,"lat":40.137176,"stopid":28946,"stopname":"High St &amp; Taylor St"},{"lng":-75.521849,"lat":40.137464,"stopid":28947,"stopname":"High St &amp; Fairview St"},{"lng":-75.518807,"lat":40.137885,"stopid":28948,"stopname":"High St &amp; Franklin St"},{"lng":-75.515187,"lat":40.130569,"stopid":28951,"stopname":"Main St &amp; Washington Av"},{"lng":-75.514878,"lat":40.129569,"stopid":28952,"stopname":"Main St &amp; 1st Av"},{"lng":-75.514261,"lat":40.127642,"stopid":28954,"stopname":"Main St &amp; 3rd Av"},{"lng":-75.51356,"lat":40.125456,"stopid":28956,"stopname":"Main St &amp; 5th Av - FS"},{"lng":-75.51312,"lat":40.124126,"stopid":28957,"stopname":"Main St &amp; Nutt Rd"},{"lng":-75.503492,"lat":40.11999,"stopid":28962,"stopname":"Valley Forge Rd &amp; Whitehorse Rd"},{"lng":-75.498178,"lat":40.120261,"stopid":28964,"stopname":"Valley Forge Rd &amp; Dorchester Way"},{"lng":-75.487522,"lat":40.1175,"stopid":28965,"stopname":"Valley Forge Rd &amp; Pawlings Rd"},{"lng":-75.484929,"lat":40.115216,"stopid":28966,"stopname":"Valley Forge Rd &amp; Lafayette Cr"},{"lng":-75.477774,"lat":40.106516,"stopid":28970,"stopname":"Valley Forge Rd &amp; Eastgate Dr"},{"lng":-75.461428,"lat":40.099872,"stopid":28972,"stopname":"Valley Forge Rd &amp; Valley Creek Rd -"},{"lng":-75.438661,"lat":40.104169,"stopid":28975,"stopname":"Valley Forge Park Dr &amp; Washingtom M"},{"lng":-75.420567,"lat":40.10075,"stopid":28977,"stopname":"North Gulph Rd &amp; Valley Forge Rd"},{"lng":-75.399389,"lat":40.091937,"stopid":28978,"stopname":"Goddard Blvd &amp; Mall Blvd - MBFS"},{"lng":-75.408347,"lat":40.088958,"stopid":28979,"stopname":"Goddard Blvd &amp; North Gulph Rd"},{"lng":-75.408039,"lat":40.089119,"stopid":28980,"stopname":"Goddard Blvd &amp; North Gulph Rd - FS"},{"lng":-75.397319,"lat":40.091169,"stopid":28981,"stopname":"Goddard Blvd &amp; Mall Blvd - 2 MBNS"},{"lng":-75.553896,"lat":40.176933,"stopid":29695,"stopname":"New St &amp; Wall St"},{"lng":-75.547839,"lat":40.181732,"stopid":29778,"stopname":"Bridge St &amp; Main St"},{"lng":-75.399779,"lat":40.092,"stopid":29779,"stopname":"Goddard Blvd &amp; Mall Blvd - 1 MBNS"},{"lng":-75.50058,"lat":40.215507,"stopid":30437,"stopname":"Ridge Pike &amp; Township Line Rd - FS"},{"lng":-75.512824,"lat":40.123867,"stopid":30502,"stopname":"Main St &amp; Nutt Rd - FS"},{"lng":-75.547259,"lat":40.181795,"stopid":30579,"stopname":"Bridge St &amp; Main St - MBFS"},{"lng":-75.530418,"lat":40.19402,"stopid":30580,"stopname":"10th Av &amp; Church St"},{"lng":-75.53164,"lat":40.19534,"stopid":30581,"stopname":"10th Av &amp; Royersford Rd"},{"lng":-75.531723,"lat":40.195509,"stopid":30582,"stopname":"Royersford Rd &amp; 10th Av"},{"lng":-75.529552,"lat":40.193253,"stopid":30583,"stopname":"10th &amp; Main St"},{"lng":-75.507565,"lat":40.12147,"stopid":30584,"stopname":"Valley Forge Rd &amp; Kleyona Av"},{"lng":-75.516482,"lat":40.133862,"stopid":30620,"stopname":"Bridge St &amp; Main St"},{"lng":-75.51244,"lat":40.201977,"stopid":31133,"stopname":"Township Line Rd &amp; Rittenhouse Rd"},{"lng":-75.507563,"lat":40.206961,"stopid":31134,"stopname":"Township Line Rd &amp; Linfield Rd"},{"lng":-75.500957,"lat":40.213659,"stopid":31135,"stopname":"Township Line Rd &amp; Ridge Pk - MBNS"},{"lng":-75.501813,"lat":40.216265,"stopid":31136,"stopname":"Ridge Pike &amp; Township Line Rd - MBF"},{"lng":-75.507492,"lat":40.2073,"stopid":31138,"stopname":"Township Line Rd &amp; Linfield Rd"},{"lng":-75.512784,"lat":40.201914,"stopid":31139,"stopname":"Township Line &amp; Rittenhouse Rd"},{"lng":-75.472492,"lat":40.099681,"stopid":31193,"stopname":"Valley Forge Rd &amp; Valley Park Rd - "},{"lng":-75.471296,"lat":40.099253,"stopid":31194,"stopname":"Valley Forge Rd &amp; Valley Park Rd - "},{"lng":-75.552642,"lat":40.177639,"stopid":31224,"stopname":"New St &amp; Cedar St"},{"lng":-75.553672,"lat":40.17721,"stopid":31225,"stopname":"New St &amp; Wall St"},{"lng":-75.508797,"lat":40.121933,"stopid":31268,"stopname":"Nutt Rd &amp; Starr St"},{"lng":-75.507779,"lat":40.121737,"stopid":31271,"stopname":"Nutt Rd &amp; Valley Rd"},{"lng":-75.518902,"lat":40.138019,"stopid":31272,"stopname":"High St &amp; Gay St - FS"},{"lng":-75.525721,"lat":40.199468,"stopid":32047,"stopname":"Limerick Square Shopping Center"}]