{"route": "27", "destination": "Plymouth Meeting Mall", "day": "Saturday", "stops": [{"times": ["\u2014", "\u2014", "6:45am", "\u2014", "8:04am", "8:43am", "9:22am", "10:01am", "10:40am", "11:20am", "11:53am", "12:28pm", "1:02pm", "1:37pm", "2:12pm", "2:47pm", "3:22pm", "3:57pm", "4:34pm", "5:09pm", "5:44pm", "6:19pm", "6:57pm", "7:32pm", "8:08pm", "8:43pm", "9:18pm", "10:16pm", "11:16pm"], "name": "Broad St & Christian St", "id": "5166"}, {"times": ["\u2014", "\u2014", "6:54am", "\u2014", "8:13am", "8:52am", "9:32am", "10:11am", "10:50am", "11:30am", "12:04pm", "12:39pm", "1:14pm", "1:49pm", "2:24pm", "2:59pm", "3:34pm", "4:09pm", "4:46pm", "5:21pm", "5:56pm", "6:31pm", "7:08pm", "7:43pm", "8:18pm", "8:53pm", "9:28pm", "10:26pm", "11:26pm"], "name": "15th St & JFK Blvd", "id": "17842"}, {"times": ["5:30am", "6:30am", "7:05am", "7:45am", "8:25am", "9:05am", "9:45am", "10:25am", "11:05am", "11:45am", "12:20pm", "12:55pm", "1:30pm", "2:05pm", "2:40pm", "3:15pm", "3:50pm", "4:25pm", "5:00pm", "5:35pm", "6:10pm", "6:45pm", "7:20pm", "7:55pm", "8:30pm", "9:05pm", "9:40pm", "10:38pm", "11:38pm"], "name": "Wissahickon Transportation Center", "id": "2"}, {"times": ["5:37am", "6:37am", "7:12am", "7:52am", "8:32am", "9:12am", "9:52am", "10:32am", "11:12am", "11:52am", "12:27pm", "1:02pm", "1:37pm", "2:12pm", "2:47pm", "3:22pm", "3:57pm", "4:33pm", "5:07pm", "5:42pm", "6:17pm", "6:52pm", "7:27pm", "8:02pm", "8:37pm", "9:12pm", "9:47pm", "10:45pm", "11:45pm"], "name": "Ridge Ave & Lyceum Ave", "id": "133"}, {"times": ["5:47am", "6:47am", "7:22am", "8:02am", "8:42am", "9:23am", "10:03am", "10:44am", "11:23am", "12:03pm", "12:39pm", "1:14pm", "1:49pm", "2:24pm", "2:59pm", "3:34pm", "4:09pm", "4:46pm", "5:18pm", "5:53pm", "6:27pm", "7:02pm", "7:37pm", "8:12pm", "8:47pm", "9:22pm", "9:57pm", "10:55pm", "11:55pm"], "name": "Ridge Ave & Cathedral Rd", "id": "12253"}, {"times": ["5:52am", "\u2014", "\u2014", "\u2014", "\u2014", "\u2014", "\u2014", "\u2014", "\u2014", "\u2014", "\u2014", "\u2014", "\u2014", "\u2014", "\u2014", "\u2014", "\u2014", "\u2014", "\u2014", "\u2014", "\u2014", "\u2014", "\u2014", "\u2014", "\u2014", "\u2014", "\u2014", "\u2014", "12:00am"], "name": "Church & Germantown (Barren Hill)", "id": "511"}, {"times": ["\u2014", "6:59am", "7:35am", "8:15am", "8:55am", "9:37am", "10:18am", "10:59am", "11:39am", "12:20pm", "12:56pm", "1:30pm", "2:05pm", "2:40pm", "3:15pm", "3:50pm", "4:25pm", "5:02pm", "5:32pm", "6:07pm", "6:40pm", "7:14pm", "7:49pm", "8:24pm", "8:59pm", "9:33pm", "10:08pm", "11:06pm", "\u2014"], "name": "Metroplex Center", "id": "19047"}, {"times": ["\u2014", "7:05am", "7:41am", "8:21am", "9:01am", "9:44am", "10:25am", "11:06am", "11:46am", "12:27pm", "1:03pm", "1:37pm", "2:13pm", "2:48pm", "3:23pm", "3:58pm", "4:32pm", "5:09pm", "5:39pm", "6:14pm", "6:47pm", "7:20pm", "7:55pm", "8:30pm", "9:05pm", "9:39pm", "10:13pm", "11:11pm", "\u2014"], "name": "Plymouth Meeting Mall", "id": "30125"}]}