{"route": "123", "destination": "King of Prussia", "day": "Sunday", "stops": [{"times": ["7:55am", "8:55am", "9:25am", "9:55am", "10:25am", "10:55am", "11:25am", "11:55am", "12:25pm", "12:55pm", "1:25pm", "1:55pm", "2:25pm", "2:55pm", "3:25pm", "4:00pm", "5:00pm", "6:15pm"], "name": "69th Street Transportation Center", "id": "2024"}, {"times": ["8:06am", "9:06am", "9:36am", "10:06am", "10:36am", "11:06am", "11:36am", "12:06pm", "12:36pm", "1:06pm", "1:36pm", "2:06pm", "2:36pm", "3:06pm", "3:36pm", "4:11pm", "5:11pm", "6:26pm"], "name": "Manoa (West Chester Pike & Eagle)", "id": "1983"}, {"times": ["8:26am", "9:26am", "9:56am", "10:26am", "10:56am", "11:26am", "11:56am", "12:26pm", "12:56pm", "1:29pm", "1:59pm", "2:29pm", "2:59pm", "3:29pm", "3:59pm", "4:34pm", "5:31pm", "6:46pm"], "name": "King Of Prussia Plaza Transit Center", "id": "1827"}]}