{"route": "28", "destination": "Fern Rock Transportation Center", "day": "Sunday", "stops": [{"times": ["8:02am", "9:17am", "10:32am", "11:47am", "1:02pm", "2:17pm", "3:32pm", "4:45pm", "6:00pm"], "name": "Torresdale & Cottman Loop", "id": "523"}, {"times": ["8:06am", "9:21am", "10:36am", "11:51am", "1:06pm", "2:21pm", "3:36pm", "4:49pm", "6:04pm"], "name": "Torresdale Ave & Rhawn St", "id": "524"}, {"times": ["8:13am", "9:28am", "10:43am", "11:58am", "1:13pm", "2:28pm", "3:43pm", "4:55pm", "6:10pm"], "name": "Roosevelt Blvd & Rhawn St", "id": "525"}, {"times": ["8:17am", "9:32am", "10:47am", "12:02pm", "1:17pm", "2:32pm", "3:47pm", "4:58pm", "6:13pm"], "name": "Castor Ave & Rhawn St", "id": "526"}, {"times": ["8:24am", "9:39am", "10:54am", "12:09pm", "1:24pm", "2:39pm", "3:54pm", "5:04pm", "6:19pm"], "name": "Oxford Ave & Rhawn St", "id": "527"}, {"times": ["8:31am", "9:46am", "11:01am", "12:16pm", "1:31pm", "2:46pm", "4:01pm", "5:10pm", "6:25pm"], "name": "Fox Chase Rd & Forrest Ave", "id": "469"}, {"times": ["8:38am", "9:53am", "11:08am", "12:23pm", "1:38pm", "2:53pm", "4:08pm", "5:16pm", "6:31pm"], "name": "Harrison Ave & High School Rd", "id": "529"}, {"times": ["8:48am", "10:03am", "11:18am", "12:33pm", "1:48pm", "3:03pm", "4:18pm", "5:25pm", "6:40pm"], "name": "Fern Rock Transportation Center", "id": "841"}]}