{"route": "127", "destination": "Oxford Valley Mall", "day": "Weekday", "stops": [{"times": ["5:42am", "6:50am", "8:05am", "9:23am", "10:15am", "11:45am", "1:15pm", "2:45pm", "4:20pm", "5:15pm", "6:15pm", "7:05pm", "8:00pm"], "name": "Trenton Transit Center", "id": "1754"}, {"times": ["5:52am", "7:00am", "8:16am", "9:34am", "10:26am", "11:56am", "1:26pm", "2:56pm", "4:33pm", "5:28pm", "6:26pm", "7:16pm", "8:11pm"], "name": "Pennsylvania Av and Bridge St (Morrisville)", "id": "28040"}, {"times": ["5:56am", "7:04am", "8:21am", "9:39am", "10:31am", "12:02pm", "1:31pm", "3:01pm", "4:39pm", "5:34pm", "6:33pm", "7:21pm", "8:15pm"], "name": "West Trenton Av and Pine Grove Rd", "id": "28055"}, {"times": ["6:03am", "7:13am", "8:29am", "9:47am", "10:38am", "12:10pm", "1:39pm", "3:10pm", "4:49pm", "5:43pm", "6:42pm", "7:29pm", "8:23pm"], "name": "Trenton and Tyburn Rds (Fallsington)", "id": "30334"}, {"times": ["6:11am", "7:22am", "8:38am", "9:55am", "10:47am", "12:19pm", "1:48pm", "3:19pm", "4:57pm", "5:52pm", "6:50pm", "7:37pm", "8:32pm"], "name": "Kenwood Dr N and Levittown Pkwy", "id": "28077"}, {"times": ["6:19am", "7:31am", "8:47am", "10:04am", "10:55am", "12:28pm", "1:56pm", "3:27pm", "5:05pm", "6:01pm", "6:58pm", "7:45pm", "8:41pm"], "name": "Oxford Valley Rd and Olds Blvd (Fairless Hills)", "id": "1761"}, {"times": ["6:25am", "7:37am", "8:52am", "10:11am", "11:02am", "12:35pm", "2:02pm", "3:33pm", "5:11pm", "6:07pm", "7:04pm", "7:51pm", "8:46pm"], "name": "Sesame Place", "id": "1762"}, {"times": ["6:30am", "7:42am", "8:57am", "10:16am", "11:07am", "12:40pm", "2:07pm", "3:38pm", "5:16pm", "6:12pm", "7:09pm", "7:56pm", "8:51pm"], "name": "Oxford Valley Mall", "id": "332"}]}