{"route": "95", "destination": "Willow Grove Park Mall", "day": "Weekday", "stops": [{"times": ["5:53am", "6:17am", "6:42am", "7:00am", "7:25am", "7:50am", "8:27am", "8:50am", "9:52am", "10:51am", "11:50am", "12:52pm", "1:51pm", "2:51pm", "3:33pm", "4:10pm", "4:25pm", "5:16pm", "5:30pm", "6:12pm", "6:54pm"], "name": "Gulph Mills Station", "id": "30332"}, {"times": ["5:59am", "6:23am", "6:49am", "7:05am", "7:30am", "7:56am", "8:33am", "8:56am", "9:58am", "10:57am", "11:55am", "12:58pm", "1:57pm", "2:56pm", "3:39pm", "4:16pm", "4:31pm", "5:22pm", "5:35pm", "6:18pm", "7:00pm"], "name": "Horizon Blvd & Church Rd", "id": "1639"}, {"times": ["6:05am", "6:29am", "6:55am", "7:11am", "7:36am", "8:03am", "8:40am", "9:02am", "10:04am", "11:03am", "12:01pm", "1:04pm", "2:03pm", "3:02pm", "3:44pm", "4:22pm", "4:38pm", "5:29pm", "5:42pm", "6:24pm", "7:07pm"], "name": "River Rd at The Inquirer", "id": "1638"}, {"times": ["6:12am", "\u2014", "7:01am", "\u2014", "\u2014", "8:12am", "8:49am", "9:10am", "10:11am", "11:11am", "12:09pm", "1:10pm", "2:10pm", "3:09pm", "\u2014", "4:34pm", "\u2014", "5:43pm", "5:56pm", "6:36pm", "7:14pm"], "name": "Conshohocken Station", "id": "15178"}, {"times": ["6:28am", "\u2014", "7:17am", "\u2014", "\u2014", "8:32am", "\u2014", "9:28am", "10:28am", "11:27am", "12:28pm", "1:27pm", "2:27pm", "3:28pm", "\u2014", "4:52pm", "\u2014", "6:02pm", "\u2014", "6:52pm", "7:29pm"], "name": "Metroplex Shopping Center", "id": "1636"}, {"times": ["6:35am", "\u2014", "7:24am", "\u2014", "\u2014", "8:41am", "\u2014", "9:36am", "10:36am", "11:36am", "12:36pm", "1:35pm", "2:35pm", "3:35pm", "\u2014", "5:03pm", "\u2014", "6:13pm", "\u2014", "6:59pm", "7:38pm"], "name": "Plymouth Meeting Mall", "id": "246"}, {"times": ["6:43am", "\u2014", "7:32am", "\u2014", "\u2014", "8:49am", "\u2014", "9:44am", "10:43am", "11:42am", "12:43pm", "1:42pm", "2:44pm", "3:41pm", "\u2014", "5:14pm", "\u2014", "6:23pm", "\u2014", "7:06pm", "\u2014"], "name": "Norristown Rd at Sentry Park Office Center", "id": "27624"}, {"times": ["6:53am", "\u2014", "7:42am", "\u2014", "\u2014", "8:58am", "\u2014", "9:52am", "10:51am", "11:50am", "12:51pm", "1:50pm", "2:53pm", "3:51pm", "\u2014", "5:26pm", "\u2014", "6:32pm", "\u2014", "7:14pm", "\u2014"], "name": "Butler Av and Main St (Ambler Station)", "id": "1687"}, {"times": ["7:00am", "\u2014", "7:49am", "\u2014", "\u2014", "9:05am", "\u2014", "9:59am", "10:57am", "11:56am", "12:58pm", "1:56pm", "2:59pm", "3:57pm", "\u2014", "5:33pm", "\u2014", "6:38pm", "\u2014", "7:20pm", "\u2014"], "name": "Pennsylvania Av and Summit Av (Fort Washington Station)", "id": "29774"}, {"times": ["7:07am", "\u2014", "7:56am", "\u2014", "\u2014", "9:12am", "\u2014", "10:06am", "11:03am", "12:03pm", "1:05pm", "2:03pm", "3:07pm", "4:05pm", "\u2014", "5:40pm", "\u2014", "6:44pm", "\u2014", "7:26pm", "\u2014"], "name": "North Hills and Chestnut Avs (North Hills)", "id": "27652"}, {"times": ["7:20am", "\u2014", "8:09am", "\u2014", "\u2014", "9:25am", "\u2014", "10:20am", "11:16am", "12:17pm", "1:19pm", "2:17pm", "3:21pm", "4:21pm", "\u2014", "5:53pm", "\u2014", "6:57pm", "\u2014", "7:39pm", "\u2014"], "name": "Willow Grove Park Mall", "id": "809"}]}