{"route": "34", "destination": "13th-Market", "day": "Saturday", "stops": [{"times": ["5:02am", "5:32am", "5:57am", "6:19am", "6:39am", "6:59am", "7:19am", "7:39am", "7:58am", "8:16am", "8:31am", "8:46am", "9:00am", "9:15am", "9:30am", "9:45am", "10:00am", "10:15am", "10:30am", "10:45am", "11:00am", "11:15am", "11:30am", "11:44am", "11:58am", "12:11pm", "12:23pm", "12:35pm", "12:47pm", "12:59pm", "1:11pm", "1:23pm", "1:35pm", "1:47pm", "1:59pm", "2:11pm", "2:23pm", "2:35pm", "2:47pm", "2:59pm", "3:14pm", "3:29pm", "3:44pm", "3:59pm", "4:14pm", "4:29pm", "4:45pm", "5:00pm", "5:15pm", "5:30pm", "5:45pm", "6:01pm", "6:16pm", "6:31pm", "6:46pm", "7:01pm", "7:16pm", "7:31pm", "7:46pm", "8:03pm", "8:23pm", "8:43pm", "9:03pm", "9:23pm", "9:43pm", "10:08pm", "10:33pm", "10:59pm", "11:29pm", "11:59pm", "12:29am", "1:00am"], "name": "61st St & Baltimore Ave", "id": "599"}, {"times": ["5:09am", "5:39am", "6:05am", "6:27am", "6:47am", "7:07am", "7:27am", "7:47am", "8:06am", "8:24am", "8:39am", "8:54am", "9:09am", "9:24am", "9:39am", "9:54am", "10:09am", "10:24am", "10:39am", "10:54am", "11:09am", "11:24am", "11:39am", "11:53am", "12:07pm", "12:20pm", "12:32pm", "12:44pm", "12:56pm", "1:08pm", "1:20pm", "1:32pm", "1:44pm", "1:56pm", "2:08pm", "2:20pm", "2:32pm", "2:44pm", "2:56pm", "3:08pm", "3:23pm", "3:38pm", "3:53pm", "4:08pm", "4:23pm", "4:38pm", "4:54pm", "5:09pm", "5:24pm", "5:39pm", "5:54pm", "6:09pm", "6:24pm", "6:39pm", "6:54pm", "7:09pm", "7:24pm", "7:39pm", "7:54pm", "8:11pm", "8:31pm", "8:51pm", "9:11pm", "9:31pm", "9:51pm", "10:16pm", "10:41pm", "11:06pm", "11:36pm", "12:06am", "12:36am", "1:07am"], "name": "49th St & Baltimore Ave", "id": "600"}, {"times": ["5:14am", "5:44am", "6:11am", "6:33am", "6:53am", "7:13am", "7:33am", "7:53am", "8:13am", "8:31am", "8:46am", "9:01am", "9:16am", "9:31am", "9:46am", "10:01am", "10:16am", "10:31am", "10:46am", "11:01am", "11:16am", "11:31am", "11:46am", "12:00pm", "12:14pm", "12:27pm", "12:39pm", "12:51pm", "1:03pm", "1:15pm", "1:27pm", "1:39pm", "1:51pm", "2:03pm", "2:15pm", "2:27pm", "2:39pm", "2:51pm", "3:03pm", "3:15pm", "3:30pm", "3:45pm", "4:00pm", "4:15pm", "4:30pm", "4:45pm", "5:00pm", "5:15pm", "5:30pm", "5:45pm", "6:00pm", "6:15pm", "6:30pm", "6:45pm", "7:00pm", "7:15pm", "7:30pm", "7:45pm", "8:00pm", "8:17pm", "8:37pm", "8:57pm", "9:17pm", "9:37pm", "9:57pm", "10:22pm", "10:47pm", "11:12pm", "11:42pm", "12:12am", "12:42am", "1:12am"], "name": "40th St Trolley Portal", "id": "20804"}, {"times": ["5:24am", "5:54am", "6:22am", "6:44am", "7:04am", "7:24am", "7:44am", "8:04am", "8:24am", "8:42am", "8:57am", "9:12am", "9:27am", "9:42am", "9:57am", "10:12am", "10:27am", "10:42am", "10:57am", "11:12am", "11:27am", "11:42am", "11:57am", "12:11pm", "12:25pm", "12:38pm", "12:50pm", "1:02pm", "1:14pm", "1:26pm", "1:38pm", "1:50pm", "2:02pm", "2:14pm", "2:26pm", "2:38pm", "2:50pm", "3:02pm", "3:14pm", "3:26pm", "3:41pm", "3:56pm", "4:11pm", "4:26pm", "4:41pm", "4:56pm", "5:11pm", "5:26pm", "5:41pm", "5:56pm", "6:11pm", "6:26pm", "6:41pm", "6:56pm", "7:11pm", "7:26pm", "7:41pm", "7:56pm", "8:10pm", "8:27pm", "8:47pm", "9:07pm", "9:27pm", "9:47pm", "10:07pm", "10:32pm", "10:57pm", "11:22pm", "11:52pm", "12:22am", "12:52am", "1:22am"], "name": "13th and Market Sts", "id": "283"}]}